qrookDB/DB.py
qrookDB/DI.py
qrookDB/IConnector.py
qrookDB/PostgresConnector.py
qrookDB/SQLiteConnector.py
qrookDB/__init__.py
qrookDB/data.py
qrookDB/data_formatter.py
qrookDB/error_handlers.py
qrookDB/example_run.py
qrookDB/operators.py
qrookDB/qrlogging.py
qrookDB/query.py
qrookDB/query_parts.py
qrookDB/sqlite_example_run.py
qrookDB/symbols.py
qrookDB/test_all.py
qrookDB/tests.py
qrook_db/DB.py
qrook_db/DI.py
qrook_db/IConnector.py
qrook_db/PostgresConnector.py
qrook_db/__init__.py
qrook_db/data.py
qrook_db/data_formatter.py
qrook_db/error_handlers.py
qrook_db/example_run.py
qrook_db/operators.py
qrook_db/qrlogging.py
qrook_db/query.py
qrook_db/query_parts.py
qrook_db/symbols.py
qrook_db/tests.py
qrookDB-1.3.3.1.dist-info/LICENSE
qrookDB-1.3.3.1.dist-info/METADATA
qrookDB-1.3.3.1.dist-info/WHEEL
qrookDB-1.3.3.1.dist-info/top_level.txt
qrookDB-1.3.3.1.dist-info/RECORD
