Metadata-Version: 2.1
Name: qrookDB
Version: 1.3.3.1
Summary: tiny ORM for SQL-databases
Home-page: https://github.com/Kurush7/qrook_db
Author: Kurush
Author-email: ze17@ya.ru
License: UNKNOWN
Platform: UNKNOWN
Classifier: Programming Language :: Python :: 3.6
Classifier: Operating System :: OS Independent
Requires-Python: >=3.6
License-File: LICENSE
